[
  {
    "flag": "🇧🇷",
    "title": "Pontos.CC",
    "subtitle": "",
    "url": "https:\/\/pontos.cc",
    "avatar": "/logos/pontoscc-avatar.svg"
  },
  {
    "flag": "🇧🇷",
    "title": "@pedrolandau",
    "subtitle": "",
    "url": "https://instagram.com/pedrolandau",
    "avatar": "/logos/pl-full-blue.svg"
  },
  {
    "flag": "🇧🇷",
    "title": "Viagens fora do comum",
    "subtitle": "",
    "url": "https://www.youtube.com/@viagensforadocomum",
    "avatar": "/logos/VFDC_Logo_Vertical Positivo.svg"
  }
]
